mathsimple/__init__.py
mathsimple/geometry.py
mathsimple/operations.py
mathtiar-0.1.1.dist-info/METADATA
mathtiar-0.1.1.dist-info/WHEEL
mathtiar-0.1.1.dist-info/top_level.txt
mathtiar-0.1.1.dist-info/RECORD
