Metadata-Version: 2.1
Name: mathtiar
Version: 0.1.1
Summary: Simple Math
Home-page: https://github.com/szzin20/simple-math.git
Author: Ikhtiar Oktafio Wibowo
Author-email: tiarokta@gmail.com
License: MIT
Project-URL: Source, https://github.com/szzin20/simple-math.git
Keywords: python,math,simple
Platform: UNKNOWN
